git_clipboard/__init__.py
git_clipboard/clipboard.py
git_clipboard/cut.py
git_clipboard/paste.py
git_clipboard-0.2.3.dist-info/METADATA
git_clipboard-0.2.3.dist-info/WHEEL
git_clipboard-0.2.3.dist-info/entry_points.txt
git_clipboard-0.2.3.dist-info/licenses/LICENSE
git_clipboard-0.2.3.dist-info/RECORD
