Metadata-Version: 2.4
Name: git-clipboard
Version: 0.2.3
Summary: Cut and paste Git history safely using bundles and git-filter-repo, with strong dry-run previews
Project-URL: Homepage, https://github.com/vv111y/git-clipboard
Author: vv111y
License: MIT
License-File: LICENSE
Keywords: bundle,git,git-filter-repo,history,subtree
Classifier: Environment :: Console
Classifier: License :: OSI Approved :: MIT License
Classifier: Programming Language :: Python :: 3
Classifier: Topic :: Software Development :: Version Control :: Git
Requires-Python: >=3.8
